{
    "info": {
        "name": "DermaScan API",
        "description": "Postman collection for DermaScan API documentation.",
        "schema": "https://schema.getpostman.com/json/collection/v2.1.0/collection.json"
    },
    "item": [
        {
            "name": "Signup",
            "request": {
                "method": "POST",
                "header": [],
                "body": {
                    "mode": "raw",
                    "raw": "{\n    \"fullName\": \"John Doe\",\n    \"email\": \"johndoe@example.com\",\n    \"mobileNumber\": \"+621234567890\",\n    \"password\": \"mypassword\",\n    \"dob\": \"1990-01-01\"\n}",
                    "options": {
                        "raw": {
                            "language": "json"
                        }
                    }
                },
                "url": {
                    "raw": "http://localhost:3000/api/auth/signup",
                    "protocol": "http",
                    "host": ["localhost"],
                    "port": "3000",
                    "path": ["api", "auth", "signup"]
                }
            }
        },
        {
            "name": "Login",
            "request": {
                "method": "POST",
                "header": [],
                "body": {
                    "mode": "raw",
                    "raw": "{\n    \"email\": \"johndoe@example.com\",\n    \"password\": \"mypassword\"\n}",
                    "options": {
                        "raw": {
                            "language": "json"
                        }
                    }
                },
                "url": {
                    "raw": "http://localhost:3000/api/auth/login",
                    "protocol": "http",
                    "host": ["localhost"],
                    "port": "3000",
                    "path": ["api", "auth", "login"]
                }
            }
        },
        {
            "name": "Forgot Password",
            "request": {
                "method": "POST",
                "header": [],
                "body": {
                    "mode": "raw",
                    "raw": "{\n    \"email\": \"johndoe@example.com\",\n    \"newPassword\": \"newpassword\"\n}",
                    "options": {
                        "raw": {
                            "language": "json"
                        }
                    }
                },
                "url": {
                    "raw": "http://localhost:3000/api/auth/forgot-password",
                    "protocol": "http",
                    "host": ["localhost"],
                    "port": "3000",
                    "path": ["api", "auth", "forgot-password"]
                }
            }
        },
        {
            "name": "Add Diagnosis History",
            "request": {
                "method": "POST",
                "header": [
                    {"key": "Authorization", "value": "Bearer <jwt-token>"}
                ],
                "body": {
                    "mode": "raw",
                    "raw": "{\n    \"userId\": \"user-id\",\n    \"imageUrl\": \"http://example.com/image.jpg\",\n    \"result\": \"Dermatitis\"\n}",
                    "options": {
                        "raw": {
                            "language": "json"
                        }
                    }
                },
                "url": {
                    "raw": "http://localhost:3000/api/history",
                    "protocol": "http",
                    "host": ["localhost"],
                    "port": "3000",
                    "path": ["api", "history"]
                }
            }
        },
        {
            "name": "Get Diagnosis History",
            "request": {
                "method": "GET",
                "header": [
                    {"key": "Authorization", "value": "Bearer <jwt-token>"}
                ],
                "url": {
                    "raw": "http://localhost:3000/api/history/:userId",
                    "protocol": "http",
                    "host": ["localhost"],
                    "port": "3000",
                    "path": ["api", "history", ":userId"]
                }
            }
        },
        {
            "name": "Get All News",
            "request": {
                "method": "GET",
                "header": [],
                "url": {
                    "raw": "http://localhost:3000/api/news",
                    "protocol": "http",
                    "host": ["localhost"],
                    "port": "3000",
                    "path": ["api", "news"]
                }
            }
        },
        {
            "name": "Get News by ID",
            "request": {
                "method": "GET",
                "header": [],
                "url": {
                    "raw": "http://localhost:3000/api/news/:newsId",
                    "protocol": "http",
                    "host": ["localhost"],
                    "port": "3000",
                    "path": ["api", "news", ":newsId"]
                }
            }
        },
        {
            "name": "Chatbot",
            "request": {
                "method": "POST",
                "header": [],
                "body": {
                    "mode": "raw",
                    "raw": "{\n    \"message\": \"Hi, how can I get help?\"\n}",
                    "options": {
                        "raw": {
                            "language": "json"
                        }
                    }
                },
                "url": {
                    "raw": "http://localhost:3000/api/chatbot",
                    "protocol": "http",
                    "host": ["localhost"],
                    "port": "3000",
                    "path": ["api", "chatbot"]
                }
            }
        }
    ]
}
